LICENSE
MANIFEST.in
README.md
setup.cfg
setup.py
maeguias/__init__.py
maeguias/__main__.py
maeguias/exceptions.py
maeguias/plugins.py
maeguias/theme.py
maeguias.egg-info/PKG-INFO
maeguias.egg-info/SOURCES.txt
maeguias.egg-info/dependency_links.txt
maeguias.egg-info/entry_points.txt
maeguias.egg-info/not-zip-safe
maeguias.egg-info/requires.txt
maeguias.egg-info/top_level.txt
maeguias/commands/__init__.py
maeguias/commands/build.py
maeguias/commands/gh_deploy.py
maeguias/commands/new.py
maeguias/commands/serve.py
maeguias/config/__init__.py
maeguias/config/base.py
maeguias/config/config_options.py
maeguias/config/defaults.py
maeguias/contrib/__init__.py
maeguias/contrib/search/__init__.py
maeguias/contrib/search/prebuild-index.js
maeguias/contrib/search/search_index.py
maeguias/contrib/search/lunr-language/lunr.da.js
maeguias/contrib/search/lunr-language/lunr.de.js
maeguias/contrib/search/lunr-language/lunr.du.js
maeguias/contrib/search/lunr-language/lunr.es.js
maeguias/contrib/search/lunr-language/lunr.fi.js
maeguias/contrib/search/lunr-language/lunr.fr.js
maeguias/contrib/search/lunr-language/lunr.hu.js
maeguias/contrib/search/lunr-language/lunr.it.js
maeguias/contrib/search/lunr-language/lunr.jp.js
maeguias/contrib/search/lunr-language/lunr.multi.js
maeguias/contrib/search/lunr-language/lunr.no.js
maeguias/contrib/search/lunr-language/lunr.pt.js
maeguias/contrib/search/lunr-language/lunr.ro.js
maeguias/contrib/search/lunr-language/lunr.ru.js
maeguias/contrib/search/lunr-language/lunr.stemmer.support.js
maeguias/contrib/search/lunr-language/lunr.sv.js
maeguias/contrib/search/lunr-language/lunr.th.js
maeguias/contrib/search/lunr-language/lunr.tr.js
maeguias/contrib/search/templates/search/lunr.js
maeguias/contrib/search/templates/search/main.js
maeguias/contrib/search/templates/search/worker.js
maeguias/structure/__init__.py
maeguias/structure/files.py
maeguias/structure/nav.py
maeguias/structure/pages.py
maeguias/structure/toc.py
maeguias/templates/sitemap.xml
maeguias/tests/__init__.py
maeguias/tests/base.py
maeguias/tests/build_tests.py
maeguias/tests/cli_tests.py
maeguias/tests/gh_deploy_tests.py
maeguias/tests/integration.py
maeguias/tests/new_tests.py
